jftools/__init__.py
jftools/fedvr.py
jftools/interpolate.py
jftools/ipynbimport.py
jftools/myjit.py
jftools/plotting.py
jftools/shade_color.py
jftools/short_iterative_lanczos.py
jftools/tictoc.py
jftools/unroll_phase.py
jftools-0.4.2.dist-info/LICENSE
jftools-0.4.2.dist-info/WHEEL
jftools-0.4.2.dist-info/METADATA
jftools-0.4.2.dist-info/RECORD
