Metadata-Version: 2.1
Name: jftools
Version: 0.4.2
Summary: Collection of small useful helper tools for Python by Johannes Feist.
Author-email: Johannes Feist <johannes.feist@gmail.com>
Requires-Python: >=3.7
Classifier: License :: OSI Approved :: MIT License
Requires-Dist: numpy >=1.15
Requires-Dist: scipy >=1.0
Requires-Dist: numba >=0.49
Requires-Dist: nbformat >= 5.0
Requires-Dist: IPython >= 7.0
Requires-Dist: matplotlib >= 3.0
Project-URL: Home, https://github.com/jfeist/jftools
